{
    "@class": "com.kony.gen.viz.model.component.KVizUserWidget",
    "DNDConfig": null,
    "_children_": [],
    "_height_": {
        "type": "ref",
        "value": "preferred"
    },
    "_left_": {
        "type": "string",
        "value": "0dp"
    },
    "_margin_": [
        0,
        0,
        0,
        0
    ],
    "_orientation_": 1,
    "_padding_": [
        0,
        0,
        0,
        0
    ],
    "_percent_": true,
    "_skin_": "s1a710b439ce46e2af92632b3f5634b8",
    "_top_": {
        "type": "string",
        "value": "0dp"
    },
    "_width_": {
        "type": "string",
        "value": "100%"
    },
    "canUpdateUI": true,
    "containerweight": 0,
    "data": {},
    "id": "DOSBusinessCustomers",
    "info": null,
    "iscustomlayout": false,
    "isvisible": true,
    "kuid": "b321f013af0049a390c299182e471613",
    "masterType": 1,
    "name": "kony.ui.UserWidgetInstance",
    "parent": "flxScrollMain",
    "pf": "userwidgetmodel",
    "retaincontentalignment": false,
    "retainflexpositionproperties": false,
    "retainflowhorizontalalignment": false,
    "sourceUserWidget": "d570b43cdf874213a6708b619853d5d1",
    "wType": "UserWidgetInstance",
    "zindex": 1
}